jokes/__init__.py
jokes/jokes.py
jokes/jokesv2.py
py_jokes_py-1.1.3.dist-info/LICENSE
py_jokes_py-1.1.3.dist-info/METADATA
py_jokes_py-1.1.3.dist-info/WHEEL
py_jokes_py-1.1.3.dist-info/RECORD
